wblog/__init__.py
wblog/log.py
well_behaved_logging-0.0.1.dist-info/METADATA
well_behaved_logging-0.0.1.dist-info/WHEEL
well_behaved_logging-0.0.1.dist-info/top_level.txt
well_behaved_logging-0.0.1.dist-info/RECORD
