Metadata-Version: 2.1
Name: well-behaved-logging
Version: 0.0.1
Summary: UNKNOWN
Home-page: UNKNOWN
Author: Yamada Hiroyuki
License: UNKNOWN
Platform: UNKNOWN
Classifier: Programming Language :: Python
Classifier: Programming Language :: Python :: 3
Classifier: License :: OSI Approved :: MIT License
Classifier: Operating System :: OS Independent
Classifier: Development Status :: 4 - Beta
Classifier: Intended Audience :: Developers
Classifier: Topic :: Software Development :: Libraries
